setup.py
django_creek/__init__.py
django_creek/controller.py
django_creek/state.py
django_creek.egg-info/PKG-INFO
django_creek.egg-info/SOURCES.txt
django_creek.egg-info/dependency_links.txt
django_creek.egg-info/not-zip-safe
django_creek.egg-info/top_level.txt