Metadata-Version: 1.1
Name: django-creek
Version: 0.1.2
Summary: A simple flow controller for Django
Home-page: https://github.com/23andMe/django-creek
Author: Bo Lopker
Author-email: blopker@23andme.com
License: MIT License
Keywords: django
Platform: any
Classifier: Development Status :: 3 - Alpha
Classifier: Environment :: Web Environment
Classifier: Intended Audience :: Developers
Classifier: License :: OSI Approved :: MIT License
Classifier: Operating System :: OS Independent
Classifier: Programming Language :: Python
Classifier: Programming Language :: Python :: 2
Classifier: Programming Language :: Python :: 2.7
Classifier: Programming Language :: Python :: 3
Classifier: Programming Language :: Python :: 3.4
Classifier: Framework :: Django
